pruebadd/__init__.py
pruebadd/functions.py
pruebadd-0.1.1.dist-info/LICENSE
pruebadd-0.1.1.dist-info/METADATA
pruebadd-0.1.1.dist-info/WHEEL
pruebadd-0.1.1.dist-info/top_level.txt
pruebadd-0.1.1.dist-info/RECORD
